.gitignore
AUTHORS.txt
CHANGELOG.rst
CONTRIBUTING.rst
LICENSE.txt
README.rst
setup.py
tox.ini
.github/workflows/publish-sdist.yml
.github/workflows/run-tox.yml
atlas_commons/__init__.py
atlas_commons/app_utils.py
atlas_commons/exceptions.py
atlas_commons/typing.py
atlas_commons/utils.py
atlas_commons.egg-info/PKG-INFO
atlas_commons.egg-info/SOURCES.txt
atlas_commons.egg-info/dependency_links.txt
atlas_commons.egg-info/requires.txt
atlas_commons.egg-info/top_level.txt
atlas_commons/data/ca1_metadata.json
atlas_commons/data/isocortex_23_metadata.json
atlas_commons/data/isocortex_metadata.json
atlas_commons/data/metadata.json
atlas_commons/data/thalamus_metadata.json
doc/Makefile
doc/source/changelog.rst
doc/source/conf.py
doc/source/index.rst
doc/source/readme.rst
tests/1.json
tests/__init__.py
tests/test_app_utils.py
tests/test_utils.py
tests/nrrds/1.nrrd
tests/nrrds/1_direction_vectors.nrrd
tests/nrrds/1_offset.nrrd
tests/nrrds/1_shape.nrrd
tests/nrrds/1_voxel_dimensions.nrrd