Metadata-Version: 2.1
Name: atlas-commons
Version: 0.1.4
Summary: Library containing common functions to build atlases
Home-page: https://github.com/BlueBrain/atlas-commons
Author: Blue Brain Project, EPFL
License: Apache-2
Download-URL: https://github.com/BlueBrain/atlas-commons
Platform: UNKNOWN
Classifier: Development Status :: 2 - Pre-Alpha
Classifier: Programming Language :: Python
Classifier: Programming Language :: Python :: 3
Classifier: Programming Language :: Python :: 3.7
Classifier: Programming Language :: Python :: 3.8
Classifier: Programming Language :: Python :: 3.9
Classifier: Programming Language :: Python :: 3.10
Requires-Python: >=3.7.0
Provides-Extra: tests
